{
  "versions": [
    {
      "version": "v1.0.0",
      "version_title": "v1.0.0",
      "methods": [
        {
          "name": "test.create",
          "roles": [
            "TEST_WRITE"
          ],
          "doc": "Create a test item.",
          "removed_in": null,
          "job": false,
          "schemas": {
            "accepts": {
              "title": "TestCreateArgs",
              "type": "object",
              "additionalProperties": false,
              "required": [
                "data"
              ],
              "properties": {
                "data": {
                  "$ref": "#/$defs/TestCreate",
                  "description": "The item to create."
                }
              },
              "$defs": {
                "TestCreate": {
                  "title": "TestCreate",
                  "type": "object",
                  "additionalProperties": false,
                  "required": [
                    "name"
                  ],
                  "properties": {
                    "name": {
                      "title": "Name",
                      "type": "string",
                      "description": "Item name."
                    },
                    "kind": {
                      "$ref": "#/$defs/KindEnum",
                      "default": "A"
                    },
                    "tag": {
                      "enum": [
                        "RED",
                        "BLUE"
                      ],
                      "title": "TagChoice",
                      "type": "string",
                      "default": "RED",
                      "description": "Display tag."
                    }
                  }
                },
                "KindEnum": {
                  "enum": [
                    "A",
                    "B"
                  ],
                  "title": "KindEnum",
                  "type": "string",
                  "description": "Kind of item."
                }
              }
            },
            "returns": {
              "title": "TestCreateResult",
              "type": "object",
              "additionalProperties": false,
              "required": [
                "result"
              ],
              "properties": {
                "result": {
                  "$ref": "#/$defs/TestEntry",
                  "description": "The created item."
                }
              },
              "$defs": {
                "TestEntry": {
                  "title": "TestEntry",
                  "type": "object",
                  "additionalProperties": false,
                  "required": [
                    "id",
                    "name"
                  ],
                  "properties": {
                    "id": {
                      "title": "Id",
                      "type": "integer"
                    },
                    "name": {
                      "title": "Name",
                      "type": "string"
                    },
                    "kind": {
                      "$ref": "#/$defs/KindEnum"
                    }
                  }
                },
                "KindEnum": {
                  "enum": [
                    "A",
                    "B"
                  ],
                  "title": "KindEnum",
                  "type": "string",
                  "description": "Kind of item."
                }
              }
            }
          }
        },
        {
          "name": "test.update",
          "roles": [
            "TEST_WRITE"
          ],
          "doc": "Update a widget.",
          "removed_in": "v3.0.0",
          "job": false,
          "schemas": {
            "accepts": {
              "title": "TestUpdateArgs",
              "type": "object",
              "additionalProperties": false,
              "required": [
                "widget"
              ],
              "properties": {
                "widget": {
                  "$ref": "#/$defs/Widget"
                }
              },
              "$defs": {
                "Widget": {
                  "title": "Widget",
                  "type": "object",
                  "additionalProperties": false,
                  "required": [
                    "a"
                  ],
                  "properties": {
                    "a": {
                      "title": "A",
                      "type": "string"
                    }
                  }
                }
              }
            },
            "returns": {
              "title": "TestUpdateResult",
              "type": "object",
              "additionalProperties": false,
              "required": [
                "result"
              ],
              "properties": {
                "result": {
                  "type": "null"
                }
              },
              "$defs": {}
            }
          }
        },
        {
          "name": "test.get",
          "roles": [
            "TEST_READ"
          ],
          "doc": "Get the widget.",
          "removed_in": null,
          "job": false,
          "schemas": {
            "accepts": {
              "title": "TestGetArgs",
              "type": "object",
              "additionalProperties": false,
              "required": [],
              "properties": {},
              "$defs": {}
            },
            "returns": {
              "title": "TestGetResult",
              "type": "object",
              "additionalProperties": false,
              "required": [
                "result"
              ],
              "properties": {
                "result": {
                  "$ref": "#/$defs/Widget"
                }
              },
              "$defs": {
                "Widget": {
                  "title": "Widget",
                  "type": "object",
                  "additionalProperties": false,
                  "required": [
                    "a",
                    "computed"
                  ],
                  "properties": {
                    "a": {
                      "title": "A",
                      "type": "string"
                    },
                    "computed": {
                      "title": "Computed",
                      "type": "integer"
                    }
                  }
                }
              }
            }
          }
        },
        {
          "name": "test.query",
          "roles": [
            "TEST_READ"
          ],
          "doc": "Query test items.",
          "removed_in": null,
          "job": false,
          "schemas": {
            "accepts": {
              "title": "TestQueryArgs",
              "type": "object",
              "additionalProperties": false,
              "required": [],
              "properties": {
                "filters": {
                  "title": "filters",
                  "type": "array",
                  "items": {},
                  "default": [],
                  "description": "Query filters."
                },
                "options": {
                  "$ref": "#/$defs/QueryOptions",
                  "default": {}
                }
              },
              "$defs": {
                "QueryOptions": {
                  "title": "QueryOptions",
                  "type": "object",
                  "additionalProperties": false,
                  "properties": {
                    "count": {
                      "type": "boolean",
                      "default": false
                    },
                    "get": {
                      "type": "boolean",
                      "default": false
                    },
                    "limit": {
                      "type": "integer",
                      "default": 0
                    },
                    "offset": {
                      "type": "integer",
                      "default": 0
                    },
                    "order_by": {
                      "type": "array",
                      "items": {
                        "type": "string"
                      },
                      "default": []
                    },
                    "select": {
                      "type": "array",
                      "items": {},
                      "default": []
                    },
                    "extra": {
                      "type": "object",
                      "default": {}
                    },
                    "force_sql_filters": {
                      "type": "boolean",
                      "default": false
                    }
                  }
                }
              }
            },
            "returns": {
              "title": "TestQueryResult",
              "type": "object",
              "additionalProperties": false,
              "required": [
                "result"
              ],
              "properties": {
                "result": {
                  "anyOf": [
                    {
                      "type": "array",
                      "items": {
                        "$ref": "#/$defs/TestEntry"
                      }
                    },
                    {
                      "$ref": "#/$defs/TestEntry"
                    },
                    {
                      "type": "integer"
                    }
                  ]
                }
              },
              "$defs": {
                "TestEntry": {
                  "title": "TestEntry",
                  "type": "object",
                  "additionalProperties": false,
                  "required": [
                    "id",
                    "name"
                  ],
                  "properties": {
                    "id": {
                      "title": "Id",
                      "type": "integer"
                    },
                    "name": {
                      "title": "Name",
                      "type": "string"
                    },
                    "kind": {
                      "$ref": "#/$defs/KindEnum"
                    }
                  }
                },
                "KindEnum": {
                  "enum": [
                    "A",
                    "B"
                  ],
                  "title": "KindEnum",
                  "type": "string",
                  "description": "Kind of item."
                }
              }
            }
          }
        },
        {
          "name": "test.run",
          "roles": [
            "TEST_WRITE"
          ],
          "doc": "Run the long task.",
          "removed_in": null,
          "job": true,
          "schemas": {
            "accepts": {
              "title": "TestRunArgs",
              "type": "object",
              "additionalProperties": false,
              "required": [
                "id"
              ],
              "properties": {
                "id": {
                  "title": "Id",
                  "type": "integer"
                }
              },
              "$defs": {}
            },
            "returns": {
              "title": "TestRunResult",
              "type": "object",
              "additionalProperties": false,
              "required": [
                "result"
              ],
              "properties": {
                "result": {
                  "type": "boolean"
                }
              },
              "$defs": {}
            }
          }
        },
        {
          "name": "iscsi.fetch",
          "roles": [
            "TEST_READ"
          ],
          "doc": "Fetch the iSCSI thing.",
          "removed_in": null,
          "job": false,
          "schemas": {
            "accepts": {
              "title": "IscsiFetchArgs",
              "type": "object",
              "additionalProperties": false,
              "required": [],
              "properties": {},
              "$defs": {}
            },
            "returns": {
              "title": "IscsiFetchResult",
              "type": "object",
              "additionalProperties": false,
              "required": [
                "result"
              ],
              "properties": {
                "result": {
                  "$ref": "#/$defs/iSCSIThing"
                }
              },
              "$defs": {
                "iSCSIThing": {
                  "title": "iSCSIThing",
                  "type": "object",
                  "additionalProperties": false,
                  "required": [
                    "iqn"
                  ],
                  "properties": {
                    "iqn": {
                      "title": "Iqn",
                      "type": "string"
                    }
                  }
                }
              }
            }
          }
        }
      ],
      "events": [
        {
          "name": "test.changed",
          "roles": [
            "TEST_READ"
          ],
          "doc": "Sent on test item changes.",
          "removed_in": null,
          "schemas": {
            "ADDED": {
              "title": "TestChangedAddedEvent",
              "type": "object",
              "additionalProperties": false,
              "required": [
                "id"
              ],
              "properties": {
                "id": {
                  "title": "Id",
                  "type": "integer"
                },
                "fields": {
                  "$ref": "#/$defs/TestEntry"
                }
              },
              "$defs": {
                "TestEntry": {
                  "title": "TestEntry",
                  "type": "object",
                  "additionalProperties": false,
                  "required": [
                    "id",
                    "name"
                  ],
                  "properties": {
                    "id": {
                      "title": "Id",
                      "type": "integer"
                    },
                    "name": {
                      "title": "Name",
                      "type": "string"
                    },
                    "kind": {
                      "$ref": "#/$defs/KindEnum"
                    }
                  }
                },
                "KindEnum": {
                  "enum": [
                    "A",
                    "B"
                  ],
                  "title": "KindEnum",
                  "type": "string",
                  "description": "Kind of item."
                }
              }
            }
          }
        },
        {
          "name": "test.remove",
          "roles": [
            "TEST_READ"
          ],
          "doc": "Dynamic event source for test.remove progress. Middleware emits this event in every version's dump even though the method is v2-only.",
          "removed_in": null,
          "schemas": {
            "ADDED": {
              "title": "TestRemoveAddedEvent",
              "type": "object",
              "additionalProperties": false,
              "required": [
                "id"
              ],
              "properties": {
                "id": {
                  "title": "Id",
                  "type": "integer"
                }
              },
              "$defs": {}
            }
          }
        }
      ]
    },
    {
      "version": "v2.0.0",
      "version_title": "v2.0.0 (current)",
      "methods": [
        {
          "name": "test.create",
          "roles": [
            "TEST_WRITE"
          ],
          "doc": "Create a test item.",
          "removed_in": null,
          "job": false,
          "schemas": {
            "accepts": {
              "title": "TestCreateArgs",
              "type": "object",
              "additionalProperties": false,
              "required": [
                "data"
              ],
              "properties": {
                "data": {
                  "$ref": "#/$defs/TestCreate",
                  "description": "The item to create."
                }
              },
              "$defs": {
                "TestCreate": {
                  "title": "TestCreate",
                  "type": "object",
                  "additionalProperties": false,
                  "required": [
                    "name"
                  ],
                  "properties": {
                    "name": {
                      "title": "Name",
                      "type": "string",
                      "description": "Item name."
                    },
                    "kind": {
                      "$ref": "#/$defs/KindEnum",
                      "default": "A"
                    },
                    "tag": {
                      "enum": [
                        "RED",
                        "BLUE"
                      ],
                      "title": "TagChoice",
                      "type": "string",
                      "default": "RED",
                      "description": "Display tag."
                    }
                  }
                },
                "KindEnum": {
                  "enum": [
                    "A",
                    "B"
                  ],
                  "title": "KindEnum",
                  "type": "string",
                  "description": "Kind of item."
                }
              }
            },
            "returns": {
              "title": "TestCreateResult",
              "type": "object",
              "additionalProperties": false,
              "required": [
                "result"
              ],
              "properties": {
                "result": {
                  "$ref": "#/$defs/TestEntry",
                  "description": "The created item."
                }
              },
              "$defs": {
                "TestEntry": {
                  "title": "TestEntry",
                  "type": "object",
                  "additionalProperties": false,
                  "required": [
                    "id",
                    "name"
                  ],
                  "properties": {
                    "id": {
                      "title": "Id",
                      "type": "integer"
                    },
                    "name": {
                      "title": "Name",
                      "type": "string"
                    },
                    "kind": {
                      "$ref": "#/$defs/KindEnum"
                    },
                    "extra_flag": {
                      "title": "Extra Flag",
                      "type": "boolean",
                      "description": "New in v2."
                    }
                  }
                },
                "KindEnum": {
                  "enum": [
                    "A",
                    "B"
                  ],
                  "title": "KindEnum",
                  "type": "string",
                  "description": "Kind of item."
                }
              }
            }
          }
        },
        {
          "name": "test.update",
          "roles": [
            "TEST_WRITE"
          ],
          "doc": "Update a widget.",
          "removed_in": "v3.0.0",
          "job": false,
          "schemas": {
            "accepts": {
              "title": "TestUpdateArgs",
              "type": "object",
              "additionalProperties": false,
              "required": [
                "widget"
              ],
              "properties": {
                "widget": {
                  "$ref": "#/$defs/Widget"
                }
              },
              "$defs": {
                "Widget": {
                  "title": "Widget",
                  "type": "object",
                  "additionalProperties": false,
                  "required": [
                    "a"
                  ],
                  "properties": {
                    "a": {
                      "title": "A",
                      "type": "string"
                    }
                  }
                }
              }
            },
            "returns": {
              "title": "TestUpdateResult",
              "type": "object",
              "additionalProperties": false,
              "required": [
                "result"
              ],
              "properties": {
                "result": {
                  "type": "null"
                }
              },
              "$defs": {}
            }
          }
        },
        {
          "name": "test.get",
          "roles": [
            "TEST_READ"
          ],
          "doc": "Get the widget.",
          "removed_in": null,
          "job": false,
          "schemas": {
            "accepts": {
              "title": "TestGetArgs",
              "type": "object",
              "additionalProperties": false,
              "required": [],
              "properties": {},
              "$defs": {}
            },
            "returns": {
              "title": "TestGetResult",
              "type": "object",
              "additionalProperties": false,
              "required": [
                "result"
              ],
              "properties": {
                "result": {
                  "$ref": "#/$defs/Widget"
                }
              },
              "$defs": {
                "Widget": {
                  "title": "Widget",
                  "type": "object",
                  "additionalProperties": false,
                  "required": [
                    "a",
                    "computed"
                  ],
                  "properties": {
                    "a": {
                      "title": "A",
                      "type": "string"
                    },
                    "computed": {
                      "title": "Computed",
                      "type": "integer"
                    }
                  }
                }
              }
            }
          }
        },
        {
          "name": "test.query",
          "roles": [
            "TEST_READ"
          ],
          "doc": "Query test items.",
          "removed_in": null,
          "job": false,
          "schemas": {
            "accepts": {
              "title": "TestQueryArgs",
              "type": "object",
              "additionalProperties": false,
              "required": [],
              "properties": {
                "filters": {
                  "title": "filters",
                  "type": "array",
                  "items": {},
                  "default": [],
                  "description": "Query filters."
                },
                "options": {
                  "$ref": "#/$defs/QueryOptions",
                  "default": {}
                }
              },
              "$defs": {
                "QueryOptions": {
                  "title": "QueryOptions",
                  "type": "object",
                  "additionalProperties": false,
                  "properties": {
                    "count": {
                      "type": "boolean",
                      "default": false
                    },
                    "get": {
                      "type": "boolean",
                      "default": false
                    },
                    "limit": {
                      "type": "integer",
                      "default": 0
                    },
                    "offset": {
                      "type": "integer",
                      "default": 0
                    },
                    "order_by": {
                      "type": "array",
                      "items": {
                        "type": "string"
                      },
                      "default": []
                    },
                    "select": {
                      "type": "array",
                      "items": {},
                      "default": []
                    },
                    "extra": {
                      "type": "object",
                      "default": {}
                    },
                    "force_sql_filters": {
                      "type": "boolean",
                      "default": false
                    }
                  }
                }
              }
            },
            "returns": {
              "title": "TestQueryResult",
              "type": "object",
              "additionalProperties": false,
              "required": [
                "result"
              ],
              "properties": {
                "result": {
                  "anyOf": [
                    {
                      "type": "array",
                      "items": {
                        "$ref": "#/$defs/TestEntry"
                      }
                    },
                    {
                      "$ref": "#/$defs/TestEntry"
                    },
                    {
                      "type": "integer"
                    }
                  ]
                }
              },
              "$defs": {
                "TestEntry": {
                  "title": "TestEntry",
                  "type": "object",
                  "additionalProperties": false,
                  "required": [
                    "id",
                    "name"
                  ],
                  "properties": {
                    "id": {
                      "title": "Id",
                      "type": "integer"
                    },
                    "name": {
                      "title": "Name",
                      "type": "string"
                    },
                    "kind": {
                      "$ref": "#/$defs/KindEnum"
                    },
                    "extra_flag": {
                      "title": "Extra Flag",
                      "type": "boolean",
                      "description": "New in v2."
                    }
                  }
                },
                "KindEnum": {
                  "enum": [
                    "A",
                    "B"
                  ],
                  "title": "KindEnum",
                  "type": "string",
                  "description": "Kind of item."
                }
              }
            }
          }
        },
        {
          "name": "test.run",
          "roles": [
            "TEST_WRITE"
          ],
          "doc": "Run the long task.",
          "removed_in": null,
          "job": true,
          "schemas": {
            "accepts": {
              "title": "TestRunArgs",
              "type": "object",
              "additionalProperties": false,
              "required": [
                "id"
              ],
              "properties": {
                "id": {
                  "title": "Id",
                  "type": "integer"
                }
              },
              "$defs": {}
            },
            "returns": {
              "title": "TestRunResult",
              "type": "object",
              "additionalProperties": false,
              "required": [
                "result"
              ],
              "properties": {
                "result": {
                  "type": "boolean"
                }
              },
              "$defs": {}
            }
          }
        },
        {
          "name": "iscsi.fetch",
          "roles": [
            "TEST_READ"
          ],
          "doc": "Fetch the iSCSI thing.",
          "removed_in": null,
          "job": false,
          "schemas": {
            "accepts": {
              "title": "IscsiFetchArgs",
              "type": "object",
              "additionalProperties": false,
              "required": [],
              "properties": {},
              "$defs": {}
            },
            "returns": {
              "title": "IscsiFetchResult",
              "type": "object",
              "additionalProperties": false,
              "required": [
                "result"
              ],
              "properties": {
                "result": {
                  "$ref": "#/$defs/iSCSIThing"
                }
              },
              "$defs": {
                "iSCSIThing": {
                  "title": "iSCSIThing",
                  "type": "object",
                  "additionalProperties": false,
                  "required": [
                    "iqn"
                  ],
                  "properties": {
                    "iqn": {
                      "title": "Iqn",
                      "type": "string"
                    }
                  }
                }
              }
            }
          }
        },
        {
          "name": "test.remove",
          "roles": [
            "TEST_WRITE"
          ],
          "doc": "Remove a test item. New in v2.",
          "removed_in": null,
          "job": false,
          "schemas": {
            "accepts": {
              "title": "TestRemoveArgs",
              "type": "object",
              "additionalProperties": false,
              "required": [
                "id"
              ],
              "properties": {
                "id": {
                  "title": "Id",
                  "type": "integer"
                }
              },
              "$defs": {}
            },
            "returns": {
              "title": "TestRemoveResult",
              "type": "object",
              "additionalProperties": false,
              "required": [
                "result"
              ],
              "properties": {
                "result": {
                  "type": "null"
                }
              },
              "$defs": {}
            }
          }
        }
      ],
      "events": [
        {
          "name": "test.changed",
          "roles": [
            "TEST_READ"
          ],
          "doc": "Sent on test item changes.",
          "removed_in": null,
          "schemas": {
            "ADDED": {
              "title": "TestChangedAddedEvent",
              "type": "object",
              "additionalProperties": false,
              "required": [
                "id"
              ],
              "properties": {
                "id": {
                  "title": "Id",
                  "type": "integer"
                },
                "fields": {
                  "$ref": "#/$defs/TestEntry"
                }
              },
              "$defs": {
                "TestEntry": {
                  "title": "TestEntry",
                  "type": "object",
                  "additionalProperties": false,
                  "required": [
                    "id",
                    "name"
                  ],
                  "properties": {
                    "id": {
                      "title": "Id",
                      "type": "integer"
                    },
                    "name": {
                      "title": "Name",
                      "type": "string"
                    },
                    "kind": {
                      "$ref": "#/$defs/KindEnum"
                    },
                    "extra_flag": {
                      "title": "Extra Flag",
                      "type": "boolean",
                      "description": "New in v2."
                    }
                  }
                },
                "KindEnum": {
                  "enum": [
                    "A",
                    "B"
                  ],
                  "title": "KindEnum",
                  "type": "string",
                  "description": "Kind of item."
                }
              }
            }
          }
        },
        {
          "name": "test.remove",
          "roles": [
            "TEST_READ"
          ],
          "doc": "Dynamic event source for test.remove progress. Middleware emits this event in every version's dump even though the method is v2-only.",
          "removed_in": null,
          "schemas": {
            "ADDED": {
              "title": "TestRemoveAddedEvent",
              "type": "object",
              "additionalProperties": false,
              "required": [
                "id"
              ],
              "properties": {
                "id": {
                  "title": "Id",
                  "type": "integer"
                }
              },
              "$defs": {}
            }
          }
        }
      ]
    }
  ]
}